pyctmm/__init__.py
pyctmm/ctmm.dll
pyctmm/pyctmm.cp38-win_amd64.pyd
pyctmm-1.0.1.dist-info/METADATA
pyctmm-1.0.1.dist-info/WHEEL
pyctmm-1.0.1.dist-info/top_level.txt
pyctmm-1.0.1.dist-info/RECORD
