Metadata-Version: 2.1
Name: pyctmm
Version: 1.0.1
Summary: Python interface for the ctmm optical transfer matrix modelling library
Home-page: UNKNOWN
Author: Angus Bridges
Author-email: angus.bridges@npl.co.uk
License: UNKNOWN
Platform: UNKNOWN
Requires-Dist: numpy
